kappa_maki/__init__.py
kappa_maki/kappa_maki_formatter.py
kappa_maki-1.0.2.dist-info/LICENSE.txt
kappa_maki-1.0.2.dist-info/METADATA
kappa_maki-1.0.2.dist-info/WHEEL
kappa_maki-1.0.2.dist-info/RECORD
