Metadata-Version: 2.1
Name: kappa-maki
Version: 1.0.2
Summary: Formatter for generating Cucumber-format JSON test results using the Behave test framework.  Named after a refreshing cucumber sushi cocktail.
Home-page: https://github.com/TechnologyBrewery/kappa-maki
License: MIT
Author: Isaac Becerra Llanos
Author-email: ibecerrallanos@cpointe-inc.com
Requires-Python: >=3.8
Classifier: License :: OSI Approved :: MIT License
Classifier: Programming Language :: Python :: 3
Classifier: Programming Language :: Python :: 3.8
Classifier: Programming Language :: Python :: 3.9
Classifier: Programming Language :: Python :: 3.10
Classifier: Programming Language :: Python :: 3.11
Classifier: Programming Language :: Python :: 3.12
Project-URL: Repository, https://github.com/TechnologyBrewery/kappa-maki
